Subtractor/Full/full_sub.v
module full_sub(input a, b, bin,
    output diff, bout);
    assign diff=a^b^bin, bout=((!a)&b | (!(a^b))&bin);
endmodule

Subtractor/Full/full_sub_tb.v
module full_sub_tb;
    wire t_diff, t_bout;
    reg t_a, t_b, t_bin;
    full_sub sub(.a(t_a), .b(t_b), .bin(t_bin), .diff(t_diff), .bout(t_bout));
    initial begin
        $dumpfile("full.vcd");
        $dumpvars();
        $display("a\tb\tbin\tdiff\tbout");
        $monitor("%b\t%b\t%b\t%b\t%b", t_a, t_b, t_bin, t_diff, t_bout);
        t_a=1'b0;
        t_b=1'b0;
        t_bin=1'b0;
        #5
        t_a=1'b0;
        t_b=1'b0;
        t_bin=1'b1;
        #5
        t_a=1'b0;
        t_b=1'b1;
        t_bin=1'b0;
        #5
        t_a=1'b0;
        t_b=1'b1;
        t_bin=1'b1;
        #5
        t_a=1'b1;
        t_b=1'b0;
        t_bin=1'b0;
        #5
        t_a=1'b1;
        t_b=1'b0;
        t_bin=1'b1;
        #5
        t_a=1'b1;
        t_b=1'b1;
        t_bin=1'b0;
        #5
        t_a=1'b1;
        t_b=1'b1;
        t_bin=1'b1;
    end
endmodule

Subtractor/Full/full.vcd
$date
	Mon Oct 10 12:00:46 2022
$end
$version
	Icarus Verilog
$end
$timescale
	1s
$end
$scope module full_sub_tb $end
$var wire 1 ! t_diff $end
$var wire 1 " t_bout $end
$var reg 1 # t_a $end
$var reg 1 $ t_b $end
$var reg 1 % t_bin $end
$scope module sub $end
$var wire 1 # a $end
$var wire 1 $ b $end
$var wire 1 % bin $end
$var wire 1 " bout $end
$var wire 1 ! diff $end
$upscope $end
$upscope $end
$enddefinitions $end
#0
$dumpvars
0%
0$
0#
0"
0!
$end
#5
1"
1!
1%
#10
0%
1$
#15
0!
1%
#20
0"
1!
0%
0$
1#
#25
0!
1%
#30
0%
1$
#35
1"
1!
1%
