Adder/Full/full_adder.v
module full_adder(input a, b, cin,
    output sum, cout);
    assign sum=a^b^cin, cout=a&b | (a^b)&cin;
endmodule

Adder/Full/full_adder_tb.v
module full_adder_tb;
    wire t_sum, t_cout;
    reg t_a, t_b, t_cin;
    full_adder full(.a(t_a), .b(t_b), .cin(t_cin), .sum(t_sum), .cout(t_cout));
    initial begin
        $dumpfile("full.vcd");
        $dumpvars();
        $display("a\tb\tcin\tsum\tcout");
        $monitor("%b\t%b\t%b\t%b\t%b", t_a, t_b, t_cin, t_sum, t_cout);
        t_a=1'b0;
        t_b=1'b0;
        t_cin=1'b0;
        #5
        t_a=1'b0;
        t_b=1'b0;
        t_cin=1'b1;
        #5
        t_a=1'b0;
        t_b=1'b1;
        t_cin=1'b0;
        #5
        t_a=1'b0;
        t_b=1'b1;
        t_cin=1'b1;
        #5
        t_a=1'b1;
        t_b=1'b0;
        t_cin=1'b0;
        #5
        t_a=1'b1;
        t_b=1'b0;
        t_cin=1'b1;
        #5
        t_a=1'b1;
        t_b=1'b1;
        t_cin=1'b0;
        #5
        t_a=1'b1;
        t_b=1'b1;
        t_cin=1'b1;
    end
endmodule

Adder/Full/full.vcd
$date
	Mon Oct 10 11:21:36 2022
$end
$version
	Icarus Verilog
$end
$timescale
	1s
$end
$scope module full_adder_tb $end
$var wire 1 ! t_sum $end
$var wire 1 " t_cout $end
$var reg 1 # t_a $end
$var reg 1 $ t_b $end
$var reg 1 % t_cin $end
$scope module full $end
$var wire 1 # a $end
$var wire 1 $ b $end
$var wire 1 % cin $end
$var wire 1 " cout $end
$var wire 1 ! sum $end
$upscope $end
$upscope $end
$enddefinitions $end
#0
$dumpvars
0%
0$
0#
0"
0!
$end
#5
1!
1%
#10
0%
1$
#15
1"
0!
1%
#20
0"
1!
0%
0$
1#
#25
1"
0!
1%
#30
0%
1$
#35
1!
1%
